anemos/__init__.py
anemos/hello.py
anemos_py-0.0.5.dist-info/LICENSE
anemos_py-0.0.5.dist-info/METADATA
anemos_py-0.0.5.dist-info/WHEEL
anemos_py-0.0.5.dist-info/top_level.txt
anemos_py-0.0.5.dist-info/RECORD
