Metadata-Version: 2.1
Name: anemos-py
Version: 0.0.5
Summary: anemos-py: A Python library for Anemos API
Home-page: https://github.com/solufit/anemos-py
Download-URL: https://github.com/solufit/anemos-py
Author: Kengo Handa
Author-email: kengo.handa@solufit.net
Maintainer: Kengo Handa
Maintainer-email: kengo.handa@solufit.net
License: MIT License
Classifier: Intended Audience :: Science/Research
Classifier: Intended Audience :: Developers
Classifier: License :: OSI Approved :: MIT License
Classifier: Programming Language :: Python :: 3
Classifier: Programming Language :: Python :: 3.6
Classifier: Programming Language :: Python :: 3.7
Classifier: Programming Language :: Python :: 3.8
Classifier: Programming Language :: Python :: 3.9
Classifier: Programming Language :: Python :: 3 :: Only
Classifier: Topic :: Scientific/Engineering
Requires-Python: >=3.10
License-File: LICENSE
Requires-Dist: requests>=2.32.3
Requires-Dist: pydantic>=2.9.2
Provides-Extra: tutorial
